floodgate/py.typed
floodgate/floodgate.cpython-311-aarch64-linux-musl.so
floodgate/floodgate.pyi
floodgate/__init__.py
floodgate_rs-0.1.3.dist-info/RECORD
floodgate_rs-0.1.3.dist-info/WHEEL
floodgate_rs-0.1.3.dist-info/METADATA
floodgate_rs-0.1.3.dist-info/license_files/LICENSE
floodgate_rs.libs/libgcc_s-4e37474d.so.1
