Metadata-Version: 2.1
Name: floodgate-rs
Version: 0.1.3
Classifier: Programming Language :: Rust
Classifier: Programming Language :: Python :: Implementation :: CPython
Classifier: Programming Language :: Python :: Implementation :: PyPy
License-File: LICENSE
Summary: Python bindings for, a ratelimiting library written in Rust.
Keywords: cooldown,ratelimit,rate limit,rust,pyo3
License: MIT
Requires-Python: >=3.8
